gitpure-1.0.2.dist-info/METADATA
gitpure-1.0.2.dist-info/WHEEL
gitpure-1.0.2.dist-info/licenses/LICENSE
gitpure/__init__.py
gitpure/__init__.pyi
gitpure/gitpure.cpython-38-i386-linux-gnu.so
gitpure/py.typed
gitpure-1.0.2.dist-info/RECORD
