Metadata-Version: 2.4
Name: gitpure
Version: 1.0.2
Classifier: Development Status :: 4 - Beta
Classifier: Intended Audience :: Developers
Classifier: License :: OSI Approved :: MIT License
Classifier: Operating System :: OS Independent
Classifier: Programming Language :: Python :: 3
Classifier: Programming Language :: Python :: 3.8
Classifier: Programming Language :: Python :: 3.9
Classifier: Programming Language :: Python :: 3.10
Classifier: Programming Language :: Python :: 3.11
Classifier: Programming Language :: Python :: 3.12
Classifier: Programming Language :: Python :: 3.13
Classifier: Programming Language :: Python :: Implementation :: CPython
Classifier: Programming Language :: Python :: Implementation :: PyPy
Classifier: Programming Language :: Rust
Classifier: Topic :: Software Development :: Libraries :: Python Modules
Classifier: Topic :: Software Development :: Version Control
Classifier: Topic :: Software Development :: Version Control :: Git
Classifier: Typing :: Typed
Requires-Dist: pytest ; extra == 'test'
Requires-Dist: gitpython>=3.1 ; extra == 'test'
Provides-Extra: test
License-File: LICENSE
Summary: A Python git library implemented in Rust using gitoxide
Keywords: git,python,rust,gitoxide,version-control
Home-Page: https://github.com/cmeister2/gitpure
Author-email: Max Dymond <cmeister2@gmail.com>
Maintainer-email: Max Dymond <cmeister2@gmail.com>
License: MIT
Requires-Python: >=3.8
Project-URL: Homepage, https://github.com/cmeister2/gitpure
Project-URL: Documentation, https://github.com/cmeister2/gitpure
Project-URL: Repository, https://github.com/cmeister2/gitpure
Project-URL: Bug Reports, https://github.com/cmeister2/gitpure/issues
Project-URL: Source Code, https://github.com/cmeister2/gitpure
